README.md
setup.cfg
setup.py
ai_commit_msg/__init__.py
ai_commit_msg/main.py
ai_commit_msg/prepare_commit_msg_hook.py
ai_commit_msg/cli/__init__.py
ai_commit_msg/cli/config_handler.py
ai_commit_msg/cli/gen_ai_commit_message_handler.py
ai_commit_msg/cli/hook_handler.py
ai_commit_msg/core/__init__.py
ai_commit_msg/core/gen_commit_msg.py
ai_commit_msg/services/__init__.py
ai_commit_msg/services/anthropic_service.py
ai_commit_msg/services/config_service.py
ai_commit_msg/services/git_service.py
ai_commit_msg/services/local_db_service.py
ai_commit_msg/services/ollama_service.py
ai_commit_msg/services/openai_service.py
ai_commit_msg/utils/__init__.py
ai_commit_msg/utils/logger.py
ai_commit_msg/utils/models.py
ai_commit_msg/utils/utils.py
prepare_commit_msg_hooks.egg-info/PKG-INFO
prepare_commit_msg_hooks.egg-info/SOURCES.txt
prepare_commit_msg_hooks.egg-info/dependency_links.txt
prepare_commit_msg_hooks.egg-info/entry_points.txt
prepare_commit_msg_hooks.egg-info/requires.txt
prepare_commit_msg_hooks.egg-info/top_level.txt