Metadata-Version: 2.1
Name: prepare-commit-msg-hooks
Version: 0.1.4
Summary: A project to generate commit messages using AI
Home-page: https://github.com/ming1in/ai-commit-message
Author: Ming Lin
Author-email: minglianglin50@gmail.com
License: MIT
Platform: UNKNOWN
Classifier: Programming Language :: Python :: 3
Classifier: License :: OSI Approved :: MIT License
Classifier: Operating System :: OS Independent
Requires-Python: >=3.6
